mla/__init__.py
mla/attention.py
multihead_latent_attention-0.1.0.dist-info/licenses/LICENSE
multihead_latent_attention-0.1.0.dist-info/METADATA
multihead_latent_attention-0.1.0.dist-info/WHEEL
multihead_latent_attention-0.1.0.dist-info/top_level.txt
multihead_latent_attention-0.1.0.dist-info/RECORD
